rxtoolbox/__init__.py
rxtoolbox/flags/__init__.py
rxtoolbox/flags/main.py
rxtoolbox/flags/mongo.py
raenonx_toolbox-0.0.5.dist-info/LICENSE
raenonx_toolbox-0.0.5.dist-info/METADATA
raenonx_toolbox-0.0.5.dist-info/WHEEL
raenonx_toolbox-0.0.5.dist-info/top_level.txt
raenonx_toolbox-0.0.5.dist-info/RECORD
