Metadata-Version: 2.1
Name: raenonx-toolbox
Version: 0.0.5
Summary: Personal python developing toolbox.
Home-page: https://github.com/RaenonX/PyToolbox
Author: RaenonX JELLYCAT
Author-email: raenonx0710@gmail.com
License: MIT
Platform: UNKNOWN
Classifier: Development Status :: 2 - Pre-Alpha
Classifier: Environment :: Plugins
Classifier: Intended Audience :: Developers
Classifier: License :: OSI Approved :: MIT License
Classifier: Operating System :: OS Independent
Classifier: Programming Language :: Python :: 3.8
Classifier: Programming Language :: Python :: 3 :: Only
Classifier: Topic :: Utilities
Requires-Python: >=3.8
Requires-Dist: pymongo
